vizql_data_service_py/__init__.py
vizql_data_service_py/api/__init__.py
vizql_data_service_py/api/client.py
vizql_data_service_py/api/errors.py
vizql_data_service_py/api/openapi_generated.py
vizql_data_service_py/api/query_datasource.py
vizql_data_service_py/api/read_metadata.py
vizql_data_service_py/api/tableau_model.py
vizql_data_service_py/api/types.py
vizql_data_service_py/api/utils.py
vizql_data_service_py/examples/__init__.py
vizql_data_service_py/examples/async_examples.py
vizql_data_service_py/examples/common.py
vizql_data_service_py/examples/examples.py
vizql_data_service_py/examples/payload.py
vizql_data_service_py/examples/sync_examples.py
vizql_data_service_py-20253.0.0.dist-info/licenses/LICENSE.txt
vizql_data_service_py-20253.0.0.dist-info/METADATA
vizql_data_service_py-20253.0.0.dist-info/WHEEL
vizql_data_service_py-20253.0.0.dist-info/top_level.txt
vizql_data_service_py-20253.0.0.dist-info/RECORD
