Metadata-Version: 2.4
Name: vizql-data-service-py
Version: 20253.0.0
Summary: A Python client library for interacting with the VizQL Data Service API
Author-email: Tableau <github@tableau.com>
Maintainer-email: Tableau <github@tableau.com>
License-Expression: Apache-2.0
Project-URL: Homepage, https://github.com/tableau/VizQL-Data-Service/python_sdk
Project-URL: Bug Tracker, https://github.com/tableau/VizQL-Data-Service/issues
Project-URL: Source Code, https://github.com/tableau/VizQL-Data-Service/python_sdk
Keywords: vizqldataservice,tableau
Classifier: Development Status :: 4 - Beta
Classifier: Intended Audience :: Developers
Classifier: Operating System :: OS Independent
Classifier: Programming Language :: Python :: 3.9
Classifier: Programming Language :: Python :: 3.10
Classifier: Programming Language :: Python :: 3.11
Classifier: Programming Language :: Python :: 3.12
Classifier: Topic :: Software Development :: Libraries :: Python Modules
Requires-Python: >=3.9
License-File: LICENSE.txt
Requires-Dist: setuptools>=42.0.0
Requires-Dist: tableauserverclient>=0.27
Requires-Dist: python-dateutil>=2.8.0
Requires-Dist: httpx>=0.23.0
Requires-Dist: urllib3<3.0.0,>=1.25.0
Requires-Dist: attrs>=21.0.0
Requires-Dist: typing-extensions>=4.0.0
Requires-Dist: pydantic>=2.0.0
Provides-Extra: dev
Requires-Dist: pytest>=7.0.0; extra == "dev"
Requires-Dist: pytest-cov>=4.0.0; extra == "dev"
Requires-Dist: pytest-asyncio>=0.23.0; extra == "dev"
Requires-Dist: black>=23.0.0; extra == "dev"
Requires-Dist: isort>=5.0.0; extra == "dev"
Requires-Dist: flake8>=6.0.0; extra == "dev"
Requires-Dist: mypy>=1.0.0; extra == "dev"
Dynamic: license-file
